btd/sphinx/__init__.py
btd/sphinx/autoprogram.py
doc/Makefile
doc/changelog.rst
doc/cli.py
doc/cli_with_groups.py
doc/conf.py
doc/index.rst
doc/make.bat
doc/rtd-requires.txt
doc/subcmds.py
btd.sphinx.autoprogram-0.1.7.post1.dist-info/LICENSE
btd.sphinx.autoprogram-0.1.7.post1.dist-info/METADATA
btd.sphinx.autoprogram-0.1.7.post1.dist-info/WHEEL
btd.sphinx.autoprogram-0.1.7.post1.dist-info/top_level.txt
btd.sphinx.autoprogram-0.1.7.post1.dist-info/RECORD
