Metadata-Version: 2.1
Name: btd.sphinx.autoprogram
Version: 0.1.7.post1
Summary: Documenting CLI programs
Home-page: https://github.com/buildthedocs/sphinx.autoprogram
Author: Hong Minhee, Patrick Lehmann
Author-email: hong.minhee@gmail.com, Paebbels@gmail.com
License: 2-Clause BSD
Platform: any
Classifier: Development Status :: 5 - Production/Stable
Classifier: Environment :: Console
Classifier: Environment :: Web Environment
Classifier: Intended Audience :: Developers
Classifier: License :: OSI Approved :: BSD License
Classifier: Operating System :: OS Independent
Classifier: Programming Language :: Python
Classifier: Programming Language :: Python :: 3.3
Classifier: Programming Language :: Python :: 3.4
Classifier: Programming Language :: Python :: 3.5
Classifier: Programming Language :: Python :: 3.6
Classifier: Programming Language :: Python :: 3.7
Classifier: Programming Language :: Python :: 3.8
Classifier: Programming Language :: Python :: 3.9
Classifier: Programming Language :: Python :: 3.10
Classifier: Programming Language :: Python :: Implementation :: CPython
Classifier: Programming Language :: Python :: Implementation :: Stackless
Classifier: Topic :: Documentation
Classifier: Topic :: Software Development :: Documentation
Classifier: Topic :: Utilities
Requires-Dist: Sphinx (>=1.2)
Requires-Dist: six
